mcp_searxng/__init__.py
mcp_searxng/main.py
mcp_searxng/prompts.py
mcp_searxng/search.py
mcp_searxng/server.py
mcp_searxng/tools.py
mseep_mcp_searxng-0.1.3.dist-info/licenses/LICENSE
mseep_mcp_searxng-0.1.3.dist-info/METADATA
mseep_mcp_searxng-0.1.3.dist-info/WHEEL
mseep_mcp_searxng-0.1.3.dist-info/entry_points.txt
mseep_mcp_searxng-0.1.3.dist-info/top_level.txt
mseep_mcp_searxng-0.1.3.dist-info/RECORD
