Metadata-Version: 2.4
Name: mseep-mcp-searxng
Version: 0.1.3
Summary: MCP server for connecting agentic systems to search systems via searXNG
Author-email: mseep <support@skydeck.ai>
Requires-Python: >=3.12
License-File: LICENSE
Requires-Dist: httpx>=0.28.1
Requires-Dist: mcp>=1.1.2
Requires-Dist: pydantic>=2.10.3
Dynamic: license-file
